<?xml version="1.0"?>
<arts format="ascii" version="1">
<GriddedField3>
<Vector name="Pressure" nelem="46">
              110000
              101300
               88780
               77750
               67980
               59320
               51580
               44670
               38530
               33080
               28290
               24180
               20670
               17660
               15100
               12910
               11030
                9431
                8058
                6882
                5875
                5014
                4277
                3647
                3109
                2649
                2256
                1513
                1020
                 691
               470.1
                 323
               224.3
                 157
               111.3
                  79
               57.19
                29.9
                15.5
                 7.9
                   4
                   2
               0.966
                0.45
               0.202
               0.091
</Vector>
<Vector name="Latitude" nelem="1">
                   0
</Vector>
<Vector name="Longitude" nelem="1">
                   0
</Vector>
<Tensor3 name="Temperature" npages="46" nrows="1" ncols="1">
2.572000e+02
2.572000e+02
2.591000e+02
2.559000e+02
2.527000e+02
2.477000e+02
2.409000e+02
2.341000e+02
2.273000e+02
2.206000e+02
2.172000e+02
2.172000e+02
2.172000e+02
2.172000e+02
2.172000e+02
2.172000e+02
2.172000e+02
2.166000e+02
2.160000e+02
2.154000e+02
2.148000e+02
2.142000e+02
2.136000e+02
2.130000e+02
2.124000e+02
2.118000e+02
2.112000e+02
2.136000e+02
2.160000e+02
2.185000e+02
2.223000e+02
2.285000e+02
2.347000e+02
2.408000e+02
2.470000e+02
2.532000e+02
2.593000e+02
2.591000e+02
2.509000e+02
2.484000e+02
2.454000e+02
2.347000e+02
2.239000e+02
2.131000e+02
2.023000e+02
2.110000e+02
</Tensor3>
</GriddedField3>
</arts>
